gispy/__init__.py
gispy/raster.py
gispy/raster_vector.py
gispy/vector.py
gispy-0.0.10.dist-info/LICENSE
gispy-0.0.10.dist-info/METADATA
gispy-0.0.10.dist-info/WHEEL
gispy-0.0.10.dist-info/top_level.txt
gispy-0.0.10.dist-info/RECORD
